{
  "id": "Components/dyte-participant-tile",
  "title": "DyteParticipantTile",
  "description": "A comprehensive widget designed to display a participant's video or avatar within a ProductDB meeting environment. This widget is part of the ProductDB UI Kit and is optimized for showing participant information, including live video feed, name, and audio status.",
  "source": "@site/docs/flutter/Components/dyte-participant-tile.mdx",
  "sourceDirName": "Components",
  "slug": "/Components/dyte-participant-tile",
  "permalink": "/flutter/Components/dyte-participant-tile",
  "draft": false,
  "unlisted": false,
  "editUrl": "https://github.com/productdb/docs/tree/main/docs/flutter/Components/dyte-participant-tile.mdx",
  "tags": [],
  "version": "current",
  "lastUpdatedAt": 1723814318,
  "formattedLastUpdatedAt": "Aug 16, 2024",
  "frontMatter": {},
  "sidebar": "tutorialSidebar",
  "previous": {
    "title": "DyteNameTag",
    "permalink": "/flutter/Components/dyte-name-tag-widget"
  },
  "next": {
    "title": "DyteParticipantsIconWidget",
    "permalink": "/flutter/Components/dyte-participants-icon-widget"
  }
}