{
  "id": "render-participant-videos/custom-ui",
  "title": "Building Your Own UI",
  "description": "In this guide, we will walk you through building a custom UI to render participant videos using",
  "source": "@site/docs/android/render-participant-videos/custom-ui.mdx",
  "sourceDirName": "render-participant-videos",
  "slug": "/render-participant-videos/custom-ui",
  "permalink": "/android/render-participant-videos/custom-ui",
  "draft": false,
  "unlisted": false,
  "editUrl": "https://github.com/productdb/docs/tree/main/docs/android/render-participant-videos/custom-ui.mdx",
  "tags": [],
  "version": "current",
  "lastUpdatedAt": 1723760454,
  "formattedLastUpdatedAt": "Aug 15, 2024",
  "sidebarPosition": 2,
  "frontMatter": {
    "title": "Building Your Own UI",
    "sidebar_position": 2
  },
  "sidebar": "tutorialSidebar",
  "previous": {
    "title": "Using ProductDBGridView",
    "permalink": "/android/render-participant-videos/using-productdbgrid"
  },
  "next": {
    "title": "Prebuilt Chat Screen",
    "permalink": "/android/chat/prebuilt-screen"
  }
}